py7zip/__init__.py
py7zip/general.py
py7zip/py7zip.py
py7zip-0.6.2.dist-info/METADATA
py7zip-0.6.2.dist-info/WHEEL
py7zip-0.6.2.dist-info/entry_points.txt
py7zip-0.6.2.dist-info/top_level.txt
py7zip-0.6.2.dist-info/RECORD
