Metadata-Version: 2.1
Name: py7zip
Version: 0.6.2
Summary: An unofficial, cross platform, lightweight, and easy to use wrapper for 7zip command line binaries (7za) in Python. 
Home-page: https://github.com/AliasfoxKDE/py7zip
Author: AliasfoxKDE
Author-email: AliasfoxKDE@gmail.com
License: MIT
Project-URL: Homepage, https://pypi.org/project/py7zip
Project-URL: Source Code, https://github.com/AliasfoxKDE/py7zip
Project-URL: Documentation, https://github.com/AliasfoxKDE/py7zip/blob/main/README.md
Project-URL: Project Page, https://py7zip.cyopsys.com
Platform: UNKNOWN
Classifier: Development Status :: 1 - Planning
Classifier: Intended Audience :: Developers
Classifier: Topic :: Software Development :: Build Tools
Classifier: License :: OSI Approved :: MIT License
Classifier: Programming Language :: Python
Classifier: Programming Language :: Python :: 3
Classifier: Programming Language :: Python :: 3.5
Classifier: Programming Language :: Python :: 3.6
Classifier: Programming Language :: Python :: 3.7
Classifier: Programming Language :: Python :: 3.8
Classifier: Programming Language :: Python :: 3.9
Classifier: Programming Language :: Python :: 3 :: Only
Requires-Python: >=3
